bungied2auth/__init__.py
bungied2auth/oauth.py
bungie_d2_oauth-0.0.5.dist-info/LICENSE
bungie_d2_oauth-0.0.5.dist-info/METADATA
bungie_d2_oauth-0.0.5.dist-info/WHEEL
bungie_d2_oauth-0.0.5.dist-info/top_level.txt
bungie_d2_oauth-0.0.5.dist-info/RECORD
